catalog_books/__init__.py
catalog_books/admin.py
catalog_books/apps.py
catalog_books/cms_appconfig.py
catalog_books/cms_apps.py
catalog_books/cms_menus.py
catalog_books/cms_plugins.py
catalog_books/cms_toolbars.py
catalog_books/constants.py
catalog_books/forms.py
catalog_books/models.py
catalog_books/url_converters.py
catalog_books/urls.py
catalog_books/views.py
catalog_books/locale/cs/LC_MESSAGES/django.mo
catalog_books/locale/cs/LC_MESSAGES/django.po
catalog_books/migrations/0001_initial.py
catalog_books/migrations/0002_create_default_config.py
catalog_books/migrations/0003_remove_book_highlight_book_bestseller_book_new.py
catalog_books/migrations/0004_book_bibliographic_description_book_dimensions_and_more.py
catalog_books/migrations/0005_book_sample.py
catalog_books/migrations/0006_buttonsubmit.py
catalog_books/migrations/0007_buttonsubmit_title.py
catalog_books/migrations/0008_book_coming_soon.py
catalog_books/migrations/__init__.py
catalog_books/static/catalog_books/img/list-type.svg
catalog_books/static/catalog_books/img/tiles-type.svg
catalog_books/static/catalog_books/img/without-cover-cs.svg
catalog_books/static/catalog_books/img/without-cover-en.svg
catalog_books/templates/catalog_books/base.html
catalog_books/templates/catalog_books/base_list.html
catalog_books/templates/catalog_books/book_detail.html
catalog_books/templates/catalog_books/book_list.html
catalog_books/templates/catalog_books/book_list_order_by.html
catalog_books/templates/catalog_books/book_tiles.html
catalog_books/templates/catalog_books/button.html
catalog_books/templates/catalog_books/pagination.html
catalog_books/templates/catalog_books/plugin.html
catalog_books/templatetags/__init__.py
catalog_books/templatetags/catalog_books.py
catalog_books/tests/__init__.py
catalog_books/tests/test_models.py
djangocms_catalog_books-2.0.2.dist-info/METADATA
djangocms_catalog_books-2.0.2.dist-info/WHEEL
djangocms_catalog_books-2.0.2.dist-info/top_level.txt
djangocms_catalog_books-2.0.2.dist-info/RECORD
