Metadata-Version: 2.4
Name: djangocms-catalog-books
Version: 2.0.2
Summary: DjangoCMS Catalog of Books
Home-page: https://gitlab.nic.cz/djangocms-apps/djangocms-catalog-books
Author: Zdeněk Böhm, CZ.NIC
Author-email: zdenek.bohm@nic.cz
License: GPLv3+
Platform: posix
Classifier: Typing :: Typed
Classifier: Programming Language :: Python
Classifier: Programming Language :: Python :: 3.10
Classifier: Framework :: Django CMS :: 4.1
Requires-Python: >=3.10
Requires-Dist: django-cms<6,>=4.1
Requires-Dist: aldryn-apphooks-config~=0.7
Requires-Dist: djangocms-text~=0.8
Requires-Dist: django-filer~=3.1
Requires-Dist: djangocms-aldryn-translation-tools~=1.0
Provides-Extra: quality
Requires-Dist: flake8; extra == "quality"
Requires-Dist: isort; extra == "quality"
Requires-Dist: mypy; extra == "quality"
Requires-Dist: polint; extra == "quality"
Requires-Dist: pydocstyle; extra == "quality"
